sagemakerify/__init__.py
sagemakerify/_version.py
sagemakerify/custom_lambda.py
sagemakerify/data_types.py
sagemakerify/deployment.py
sagemakerify/globals.py
sagemakerify/handler.py
sagemakerify/model.py
sagemakerify/processing.py
sagemakerify/training.py
sagemakerify/utils.py
sagemakerify/serving/__init__.py
sagemakerify/serving/setup.py
sagemakerify/serving/custom_inference/__init__.py
sagemakerify/serving/custom_inference/handler.py
sagemakerify/serving/custom_inference/serving.py
sagemakerify/serving/custom_inference/utils.py
sagemakerify-0.2.5.dist-info/LICENSE
sagemakerify-0.2.5.dist-info/METADATA
sagemakerify-0.2.5.dist-info/WHEEL
sagemakerify-0.2.5.dist-info/top_level.txt
sagemakerify-0.2.5.dist-info/RECORD
